spot_llm/__init__.py
spot_llm/models/__init__.py
spot_llm/models/gemma7b.py
spot_llm/models/hf_model.py
spot_llm/models/mistral7b.py
spot_llm/models/opt125.py
spot_llm/models/spotter.py
spot_llm/py.typed
spot_llm-0.4.0.dist-info/METADATA
spot_llm-0.4.0.dist-info/WHEEL
spot_llm-0.4.0.dist-info/RECORD
