Metadata-Version: 2.1
Name: spot-llm
Version: 0.4.0
Summary: 
Author: Edouard Yvinec
Author-email: edouardyvinec@hotmail.fr
Requires-Python: >=3.8,<3.11
Classifier: Programming Language :: Python :: 3
Classifier: Programming Language :: Python :: 3.8
Classifier: Programming Language :: Python :: 3.9
Classifier: Programming Language :: Python :: 3.10
Requires-Dist: accelerate (>=0.30.1,<0.31.0)
Requires-Dist: loadingpy (>=0.1.4,<0.2.0)
Requires-Dist: protobuf (>=5.27.0,<6.0.0)
Requires-Dist: sentencepiece (>=0.2.0,<0.3.0)
Requires-Dist: torch (>=2.3.0,<3.0.0)
Requires-Dist: transformers (>=4.41.1,<5.0.0)
